ahk_cursor/.gitignore
ahk_cursor/Cursor.template.ahk
ahk_cursor/__main__.py
ahk_cursor/autostart.py
ahk_cursor/gen.py
ahk_cursor/main.py
ahk_cursor/mouse.ico
ahk_cursor/move_cursor.py
ahk_cursor/program.lock
ahk_cursor/running
soda_ahk_cursor-2025.8.10.0.dist-info/METADATA
soda_ahk_cursor-2025.8.10.0.dist-info/WHEEL
soda_ahk_cursor-2025.8.10.0.dist-info/entry_points.txt
soda_ahk_cursor-2025.8.10.0.dist-info/licenses/LICENSE
soda_ahk_cursor-2025.8.10.0.dist-info/RECORD
