Metadata-Version: 2.4
Name: soda-ahk-cursor
Version: 2025.8.10.0
Summary: Cursor helper
Project-URL: Repository, https://github.com/soda92/ahk-cursor
License-File: LICENSE
Requires-Python: >=3.10
Requires-Dist: pyautogui
Requires-Dist: pyinstaller>=6.15.0
Requires-Dist: pywin32>=308
